dp_app_settings/__init__.py
dp_app_settings/apps.py
dp_app_settings/models.py
dp_app_settings/tests.py
dp_app_settings/migrations/0001_initial.py
dp_app_settings/migrations/0002_auto_20181124_2153.py
dp_app_settings/migrations/__init__.py
dp_settings/__init__.py
dp_settings/apps.py
dp_settings/models.py
dp_settings/tests.py
dp_settings/migrations/0001_initial.py
dp_settings/migrations/__init__.py
dp_settings-0.0.5.dist-info/LICENSE
dp_settings-0.0.5.dist-info/METADATA
dp_settings-0.0.5.dist-info/WHEEL
dp_settings-0.0.5.dist-info/top_level.txt
dp_settings-0.0.5.dist-info/RECORD
